TangoBrowser/TangoBrowser.py
TangoBrowser/__init__.py
TangoBrowser/history.py
TangoBrowser/view.py
TangoBrowser/TreeUtility/ModelChooser.py
TangoBrowser/TreeUtility/TaurusArchivingDatabase.py
TangoBrowser/TreeUtility/TaurusDbTreeWidget.py
TangoBrowser/TreeUtility/__init__.py
TangoBrowser-1.1.10.dist-info/LICENSE
TangoBrowser-1.1.10.dist-info/METADATA
TangoBrowser-1.1.10.dist-info/WHEEL
TangoBrowser-1.1.10.dist-info/entry_points.txt
TangoBrowser-1.1.10.dist-info/top_level.txt
TangoBrowser-1.1.10.dist-info/RECORD
